otterbrix-1.0a9.data/data/lib/libotterbrix_log.a
otterbrix-1.0a9.dist-info/top_level.txt
otterbrix-1.0a9.dist-info/RECORD
otterbrix-1.0a9.dist-info/LICENSE
otterbrix-1.0a9.dist-info/METADATA
otterbrix-1.0a9.dist-info/WHEEL
otterbrix/tox.ini
otterbrix/get_path.py
otterbrix/MANIFEST.in
otterbrix/setup.py
otterbrix/pyproject.toml
otterbrix/__init__.py
otterbrix/otterbrix.cpython-37m-x86_64-linux-gnu.so
