Metadata-Version: 2.1
Name: otterbrix
Version: 1.0a9
Summary: Otterbrix: computation framework for Semi-structured data processing 
Author: 
License: 
Requires-Python: >=3.6
License-File: LICENSE
Provides-Extra: test
Requires-Dist: pytest ; extra == 'test'
